aic_flow/__init__.py
aic_flow/main.py
aic_flow/py.typed
aic_flow/graph/__init__.py
aic_flow/graph/builder.py
aic_flow/graph/state.py
aic_flow/nodes/__init__.py
aic_flow/nodes/ai.py
aic_flow/nodes/base.py
aic_flow/nodes/code.py
aic_flow/nodes/registry.py
aic_flow/nodes/telegram.py
aic_flow-0.0.1.dist-info/METADATA
aic_flow-0.0.1.dist-info/WHEEL
aic_flow-0.0.1.dist-info/licenses/LICENSE
aic_flow-0.0.1.dist-info/RECORD
