Metadata-Version: 2.4
Name: aic-flow
Version: 0.0.1
Summary: Add your description here
License-File: LICENSE
Requires-Python: >=3.12
Requires-Dist: aiosqlite>=0.21.0
Requires-Dist: fastapi>=0.104.0
Requires-Dist: langchain-community>=0.0.10
Requires-Dist: langchain-mcp-adapters>=0.1.1
Requires-Dist: langchain-openai>=0.0.5
Requires-Dist: langchain>=0.1.0
Requires-Dist: langgraph-checkpoint-postgres>=2.0.21
Requires-Dist: langgraph-checkpoint-sqlite>=2.0.7
Requires-Dist: langgraph>=0.0.10
Requires-Dist: openai>=1.0.0
Requires-Dist: pydantic>=2.4.2
Requires-Dist: python-dotenv>=1.0.0
Requires-Dist: python-telegram-bot>=22.0
Requires-Dist: selenium>=4.32.0
Requires-Dist: uvicorn>=0.24.0
Requires-Dist: websockets>=12.0
